README.rst
setup.py
Linedrive.egg-info/PKG-INFO
Linedrive.egg-info/SOURCES.txt
Linedrive.egg-info/dependency_links.txt
Linedrive.egg-info/entry_points.txt
Linedrive.egg-info/requires.txt
Linedrive.egg-info/top_level.txt
linedrive/__init__.py
linedrive/constants.py
linedrive/main.py
linedrive/utils.py
linedrive/websocket.py