Metadata-Version: 1.2
Name: Linedrive
Version: 2.0.2
Summary: A Python client for interacting with ESPN's Gamecast service. Follow gameplay events at the command line.
Home-page: https://github.com/PoorBillionaire/linedrive
Author: Adam Witt
Author-email: accidentalassist@gmail.com
License: Apache Software License
Keywords: NBA WNBA NCAA NCAAM NCAAW NHL NFL ESPN Gamecast
Platform: UNKNOWN
Classifier: Development Status :: 5 - Production/Stable
Classifier: License :: OSI Approved :: Apache Software License
Requires-Python: >=3
